covgen/__init__.py
covgen/__main__.py
covgen/localsearch/__init__.py
covgen/localsearch/avm.py
covgen/localsearch/distance_functions.py
covgen/localsearch/fitnesscalc.py
covgen/localsearch/hillclimbing.py
covgen/localsearch/trace.py
covgen/parser/__init__.py
covgen/parser/ast_parser.py
covgen/parser/walk_functiondefs.py
covgen/parser/walk_predicates.py
covgen/parser/walk_targetfunc.py
covgen/run/__init__.py
covgen/run/inputgenerator.py
covgen/test/__init__.py
covgen/test/test.py
covgen/test/test_inputgenerator.py
covgen/types/__init__.py
covgen/types/branch_tree.py
covgen/types/branchutil.py
covgen/types/function_def.py
covgen-0.0.4.dist-info/LICENSE
covgen-0.0.4.dist-info/METADATA
covgen-0.0.4.dist-info/WHEEL
covgen-0.0.4.dist-info/top_level.txt
covgen-0.0.4.dist-info/RECORD
