Metadata-Version: 2.1
Name: covgen
Version: 0.0.4
Summary: Tool for search based test data generation
Home-page: https://github.com/greenmonn/sbst-input-generator
Author: Greenmon
Author-email: greenmon@kaist.ac.kr
License: UNKNOWN
Platform: UNKNOWN
Classifier: Programming Language :: Python :: 3
Classifier: License :: OSI Approved :: MIT License
Classifier: Operating System :: OS Independent
